MANIFEST.in
setup.py
/mnt/petrelfs/xiongyuwen/DCN-v4/DCNv4/src/vision.cpp
/mnt/petrelfs/xiongyuwen/DCN-v4/DCNv4/src/cuda/dcnv4_cuda.cu
/mnt/petrelfs/xiongyuwen/DCN-v4/DCNv4/src/cuda/flash_deform_attn_cuda.cu
DCNv4/__init__.py
DCNv4.egg-info/PKG-INFO
DCNv4.egg-info/SOURCES.txt
DCNv4.egg-info/dependency_links.txt
DCNv4.egg-info/top_level.txt
DCNv4/functions/__init__.py
DCNv4/functions/dcnv4_func.py
DCNv4/functions/flash_deform_attn_func.py
DCNv4/functions/table.py
DCNv4/modules/__init__.py
DCNv4/modules/dcnv4.py
DCNv4/modules/flash_deform_attn.py
src/dcnv4.h
src/vision.cpp
src/cuda/common.h
src/cuda/dcnv4_col2im_cuda.cuh
src/cuda/dcnv4_cuda.cu
src/cuda/dcnv4_cuda.h
src/cuda/dcnv4_im2col_cuda.cuh
src/cuda/flash_deform_attn_cuda.cu
src/cuda/flash_deform_attn_cuda.h
src/cuda/flash_deform_col2im_cuda.cuh
src/cuda/flash_deform_im2col_cuda.cuh