Metadata-Version: 2.1
Name: DCNv4
Version: 1.0.4
Summary: PyTorch Wrapper for CUDA Functions of DCNv4
Home-page: UNKNOWN
Author: Feng Wang, Yuwen Xiong
License: UNKNOWN
Platform: UNKNOWN
